msl/io/__about__.py
msl/io/__init__.py
msl/io/_version.py
msl/io/base.py
msl/io/constants.py
msl/io/freezable.py
msl/io/google_api.py
msl/io/metadata.py
msl/io/node.py
msl/io/py.typed
msl/io/tables.py
msl/io/types.py
msl/io/utils.py
msl/io/readers/__init__.py
msl/io/readers/detector_responsivity_system.py
msl/io/readers/excel.py
msl/io/readers/gsheets.py
msl/io/readers/hdf5.py
msl/io/readers/json_.py
msl/io/readers/ods.py
msl/io/readers/spectrophotometer_trans_reader.py
msl/io/readers/spreadsheet.py
msl/io/readers/_xlrd/__init__.py
msl/io/readers/_xlrd/biffh.py
msl/io/readers/_xlrd/book.py
msl/io/readers/_xlrd/compdoc.py
msl/io/readers/_xlrd/formatting.py
msl/io/readers/_xlrd/formula.py
msl/io/readers/_xlrd/info.py
msl/io/readers/_xlrd/sheet.py
msl/io/readers/_xlrd/timemachine.py
msl/io/readers/_xlrd/xldate.py
msl/io/readers/_xlrd/xlsx.py
msl/io/writers/__init__.py
msl/io/writers/hdf5.py
msl/io/writers/json_.py
msl_io-0.3.0.dist-info/METADATA
msl_io-0.3.0.dist-info/WHEEL
msl_io-0.3.0.dist-info/licenses/LICENSE.txt
msl_io-0.3.0.dist-info/RECORD
