Metadata-Version: 2.4
Name: msl-io
Version: 0.3.0
Summary: Read and write data files
Project-URL: Changes, https://mslnz.github.io/msl-io/latest/release-notes/
Project-URL: Documentation, https://mslnz.github.io/msl-io/latest/
Project-URL: Homepage, https://mslnz.github.io/msl-io/latest/
Project-URL: Source, https://github.com/MSLNZ/msl-io/
Project-URL: Tracker, https://github.com/MSLNZ/msl-io/issues
Author-email: Measurement Standards Laboratory of New Zealand <info@measurement.govt.nz>
Maintainer-email: Joseph Borbely <joseph.borbely@measurement.govt.nz>
License: MIT License
License-File: LICENSE.txt
Classifier: Development Status :: 4 - Beta
Classifier: Intended Audience :: Developers
Classifier: Intended Audience :: Science/Research
Classifier: License :: OSI Approved :: MIT License
Classifier: Operating System :: OS Independent
Classifier: Programming Language :: Python
Classifier: Programming Language :: Python :: 3
Classifier: Programming Language :: Python :: 3.9
Classifier: Programming Language :: Python :: 3.10
Classifier: Programming Language :: Python :: 3.11
Classifier: Programming Language :: Python :: 3.12
Classifier: Programming Language :: Python :: 3.13
Classifier: Programming Language :: Python :: 3.14
Classifier: Topic :: Scientific/Engineering
Classifier: Topic :: Software Development
Requires-Python: >=3.9
Requires-Dist: numpy
Provides-Extra: google
Requires-Dist: google-api-python-client; extra == 'google'
Requires-Dist: google-auth-httplib2; extra == 'google'
Requires-Dist: google-auth-oauthlib; extra == 'google'
Provides-Extra: h5py
Requires-Dist: h5py; extra == 'h5py'
